{
  "buildvariants": [
    {
      "name": "generated-ubuntu",
      "display_name": "Generated Tests",
      "run_on": [
        "ubuntu2204-small"
      ],
      "tasks": [
        {
          "name": "generated-task-1",
          "activate": true
        },
        {
          "name": "generated-task-2",
          "activate": true
        }
      ],
      "activate": true
    }
  ],
  "tasks": [
    {
      "name": "generated-task-1",
      "commands": [
        {
          "command": "shell.exec",
          "params": {
            "script": "echo noop"
          }
        }
      ]
    },
    {
      "name": "generated-task-2",
      "commands": [
        {
          "command": "shell.exec",
          "params": {
            "script": "echo noop"
          }
        }
      ]
    }
  ]
}